adadpython/__init__.py
adadpython/base_pokemon.py
adadpython/dexpoke.py
adadpython/moves.py
adadpython/pokemon.py
adadpython/pypokemon.sav
adadpython/save2.npy
adadpython/saved_dexpoke.npy
adadpython/saved_movedex.npy
adadpython/texter.py
adadpython/trainerai.py
adadpython/victoryroad.py
adadpython/LICENSES/numpy_license.txt
adadpython/LICENSES/python_license.txt
adadpython/configurations/__init__.py
adadpython/configurations/config.txt
adadpython/configurations/default_config.txt
adadpython/configurations/second_config.txt
adadpython/documentation/CREDITS.txt
adadpython/documentation/game_blurb.md
adadpython/documentation/log.md
adadpython/documentation/time_ref.txt
adadpython/documentation/archive/moremon.py
adadpython/documentation/archive/saved_dexpoke.npy
adadpython/documentation/archive/saved_movedex.npy
adadpython/documentation/archive/saved_natures.npy
adadpython/documentation/archive/somemons_copy.txt
adadpython/elite5/elite_1.npy
adadpython/elite5/elite_2.npy
adadpython/elite5/elite_3.npy
adadpython/elite5/elite_4.npy
adadpython/elite5/elite_5.npy
adadpython/somemons/__init__.py
adadpython/somemons/somemons.dat
adadpython-1.0.0.dist-info/METADATA
adadpython-1.0.0.dist-info/WHEEL
adadpython-1.0.0.dist-info/licenses/LICENSE
adadpython-1.0.0.dist-info/RECORD
