Metadata-Version: 2.3
Name: adadpython
Version: 1.0.0
Summary: A package that contains a Pokémon simulation game.
Project-URL: Homepage, https://github.com/4ntoined/pokemonpy
Project-URL: Issues, https://github.com/4ntoined/pokemonpy/issues
Author: Antoine
License-File: LICENSE
Classifier: License :: OSI Approved :: GNU General Public License v3 (GPLv3)
Classifier: Operating System :: OS Independent
Classifier: Programming Language :: Python :: 3
Requires-Python: >=3.7
Requires-Dist: numpy~=1.26.4
